[{"id":1648785600,"dateTime":"2022-04-01T04:00:00.000Z","treatmentName":"massage","userId":100},{"id":1648792800,"dateTime":"2022-04-01T06:00:00.000Z","treatmentName":"massage","userId":100},{"id":1649034000,"dateTime":"2022-04-04T01:00:00.000Z","treatmentName":"massage","userId":100},{"id":1649048400,"dateTime":"2022-04-04T05:00:00.000Z","treatmentName":"facial"},{"id":1649131200,"dateTime":"2022-04-05T04:00:00.000Z","treatmentName":"scrub"},{"id":1649138400,"dateTime":"2022-04-05T06:00:00.000Z","treatmentName":"massage","userId":100},{"id":1649210400,"dateTime":"2022-04-06T02:00:00.000Z","treatmentName":"facial","userId":100},{"id":1649228400,"dateTime":"2022-04-06T07:00:00.000Z","treatmentName":"scrub","userId":100},{"id":1649289600,"dateTime":"2022-04-07T00:00:00.000Z","treatmentName":"scrub"},{"id":1649304000,"dateTime":"2022-04-07T04:00:00.000Z","treatmentName":"scrub","userId":100},{"id":1649390400,"dateTime":"2022-04-08T04:00:00.000Z","treatmentName":"massage","userId":100},{"id":1649397600,"dateTime":"2022-04-08T06:00:00.000Z","treatmentName":"massage"},{"id":1649638800,"dateTime":"2022-04-11T01:00:00.000Z","treatmentName":"massage"},{"id":1649653200,"dateTime":"2022-04-11T05:00:00.000Z","treatmentName":"facial","userId":100},{"id":1649736000,"dateTime":"2022-04-12T04:00:00.000Z","treatmentName":"scrub"},{"id":1649743200,"dateTime":"2022-04-12T06:00:00.000Z","treatmentName":"massage"},{"id":1649815200,"dateTime":"2022-04-13T02:00:00.000Z","treatmentName":"facial"},{"id":1649833200,"dateTime":"2022-04-13T07:00:00.000Z","treatmentName":"scrub"},{"id":1649894400,"dateTime":"2022-04-14T00:00:00.000Z","treatmentName":"scrub","userId":100},{"id":1649908800,"dateTime":"2022-04-14T04:00:00.000Z","treatmentName":"scrub","userId":100},{"id":1649995200,"dateTime":"2022-04-15T04:00:00.000Z","treatmentName":"massage","userId":100},{"id":1650002400,"dateTime":"2022-04-15T06:00:00.000Z","treatmentName":"massage"},{"id":1650243600,"dateTime":"2022-04-18T01:00:00.000Z","treatmentName":"massage","userId":100},{"id":1650258000,"dateTime":"2022-04-18T05:00:00.000Z","treatmentName":"facial","userId":100},{"id":1650340800,"dateTime":"2022-04-19T04:00:00.000Z","treatmentName":"scrub"},{"id":1650348000,"dateTime":"2022-04-19T06:00:00.000Z","treatmentName":"massage","userId":100},{"id":1650420000,"dateTime":"2022-04-20T02:00:00.000Z","treatmentName":"facial","userId":100},{"id":1650438000,"dateTime":"2022-04-20T07:00:00.000Z","treatmentName":"scrub","userId":100},{"id":1650499200,"dateTime":"2022-04-21T00:00:00.000Z","treatmentName":"scrub"},{"id":1650513600,"dateTime":"2022-04-21T04:00:00.000Z","treatmentName":"scrub","userId":100},{"id":1650600000,"dateTime":"2022-04-22T04:00:00.000Z","treatmentName":"massage"},{"id":1650607200,"dateTime":"2022-04-22T06:00:00.000Z","treatmentName":"massage","userId":100},{"id":1650848400,"dateTime":"2022-04-25T01:00:00.000Z","treatmentName":"massage"},{"id":1650862800,"dateTime":"2022-04-25T05:00:00.000Z","treatmentName":"facial"},{"id":1650945600,"dateTime":"2022-04-26T04:00:00.000Z","treatmentName":"scrub"},{"id":1650952800,"dateTime":"2022-04-26T06:00:00.000Z","treatmentName":"massage"},{"id":1651024800,"dateTime":"2022-04-27T02:00:00.000Z","treatmentName":"facial","userId":100},{"id":1651042800,"dateTime":"2022-04-27T07:00:00.000Z","treatmentName":"scrub"},{"id":1651104000,"dateTime":"2022-04-28T00:00:00.000Z","treatmentName":"scrub"},{"id":1651118400,"dateTime":"2022-04-28T04:00:00.000Z","treatmentName":"scrub"},{"id":1651204800,"dateTime":"2022-04-29T04:00:00.000Z","treatmentName":"massage","userId":100},{"id":1651212000,"dateTime":"2022-04-29T06:00:00.000Z","treatmentName":"massage"},{"id":1651453200,"dateTime":"2022-05-02T01:00:00.000Z","treatmentName":"massage","userId":100},{"id":1651467600,"dateTime":"2022-05-02T05:00:00.000Z","treatmentName":"facial"},{"id":1651550400,"dateTime":"2022-05-03T04:00:00.000Z","treatmentName":"scrub"},{"id":1651557600,"dateTime":"2022-05-03T06:00:00.000Z","treatmentName":"massage"},{"id":1651629600,"dateTime":"2022-05-04T02:00:00.000Z","treatmentName":"facial"},{"id":1651647600,"dateTime":"2022-05-04T07:00:00.000Z","treatmentName":"scrub"},{"id":1651708800,"dateTime":"2022-05-05T00:00:00.000Z","treatmentName":"scrub","userId":100},{"id":1651723200,"dateTime":"2022-05-05T04:00:00.000Z","treatmentName":"scrub"},{"id":1651809600,"dateTime":"2022-05-06T04:00:00.000Z","treatmentName":"massage"},{"id":1651816800,"dateTime":"2022-05-06T06:00:00.000Z","treatmentName":"massage","userId":100},{"id":1652058000,"dateTime":"2022-05-09T01:00:00.000Z","treatmentName":"massage"},{"id":1652072400,"dateTime":"2022-05-09T05:00:00.000Z","treatmentName":"facial","userId":100},{"id":1652155200,"dateTime":"2022-05-10T04:00:00.000Z","treatmentName":"scrub"},{"id":1652162400,"dateTime":"2022-05-10T06:00:00.000Z","treatmentName":"massage"},{"id":1652234400,"dateTime":"2022-05-11T02:00:00.000Z","treatmentName":"facial","userId":100},{"id":1652252400,"dateTime":"2022-05-11T07:00:00.000Z","treatmentName":"scrub"},{"id":1652313600,"dateTime":"2022-05-12T00:00:00.000Z","treatmentName":"scrub","userId":100},{"id":1652328000,"dateTime":"2022-05-12T04:00:00.000Z","treatmentName":"scrub","userId":100},{"id":1652414400,"dateTime":"2022-05-13T04:00:00.000Z","treatmentName":"massage","userId":100},{"id":1652421600,"dateTime":"2022-05-13T06:00:00.000Z","treatmentName":"massage"},{"id":1652662800,"dateTime":"2022-05-16T01:00:00.000Z","treatmentName":"massage","userId":100},{"id":1652677200,"dateTime":"2022-05-16T05:00:00.000Z","treatmentName":"facial"},{"id":1652760000,"dateTime":"2022-05-17T04:00:00.000Z","treatmentName":"scrub"},{"id":1652767200,"dateTime":"2022-05-17T06:00:00.000Z","treatmentName":"massage","userId":100},{"id":1652839200,"dateTime":"2022-05-18T02:00:00.000Z","treatmentName":"facial","userId":100},{"id":1652857200,"dateTime":"2022-05-18T07:00:00.000Z","treatmentName":"scrub"},{"id":1652918400,"dateTime":"2022-05-19T00:00:00.000Z","treatmentName":"scrub","userId":100},{"id":1652932800,"dateTime":"2022-05-19T04:00:00.000Z","treatmentName":"scrub"},{"id":1653019200,"dateTime":"2022-05-20T04:00:00.000Z","treatmentName":"massage"},{"id":1653026400,"dateTime":"2022-05-20T06:00:00.000Z","treatmentName":"massage"},{"id":1653267600,"dateTime":"2022-05-23T01:00:00.000Z","treatmentName":"massage","userId":100},{"id":1653282000,"dateTime":"2022-05-23T05:00:00.000Z","treatmentName":"facial"},{"id":1653364800,"dateTime":"2022-05-24T04:00:00.000Z","treatmentName":"scrub"},{"id":1653372000,"dateTime":"2022-05-24T06:00:00.000Z","treatmentName":"massage"},{"id":1653444000,"dateTime":"2022-05-25T02:00:00.000Z","treatmentName":"facial"},{"id":1653462000,"dateTime":"2022-05-25T07:00:00.000Z","treatmentName":"scrub","userId":100},{"id":1653523200,"dateTime":"2022-05-26T00:00:00.000Z","treatmentName":"scrub"},{"id":1653537600,"dateTime":"2022-05-26T04:00:00.000Z","treatmentName":"scrub","userId":100},{"id":1653624000,"dateTime":"2022-05-27T04:00:00.000Z","treatmentName":"massage","userId":100},{"id":1653631200,"dateTime":"2022-05-27T06:00:00.000Z","treatmentName":"massage"},{"id":1653872400,"dateTime":"2022-05-30T01:00:00.000Z","treatmentName":"massage"},{"id":1653886800,"dateTime":"2022-05-30T05:00:00.000Z","treatmentName":"facial","userId":100},{"id":1653969600,"dateTime":"2022-05-31T04:00:00.000Z","treatmentName":"scrub"},{"id":1653976800,"dateTime":"2022-05-31T06:00:00.000Z","treatmentName":"massage","userId":100},{"id":1654048800,"dateTime":"2022-06-01T02:00:00.000Z","treatmentName":"facial"},{"id":1654066800,"dateTime":"2022-06-01T07:00:00.000Z","treatmentName":"scrub"},{"id":1654128000,"dateTime":"2022-06-02T00:00:00.000Z","treatmentName":"scrub"},{"id":1654142400,"dateTime":"2022-06-02T04:00:00.000Z","treatmentName":"scrub","userId":100},{"id":1654228800,"dateTime":"2022-06-03T04:00:00.000Z","treatmentName":"massage"},{"id":1654236000,"dateTime":"2022-06-03T06:00:00.000Z","treatmentName":"massage"},{"id":1654477200,"dateTime":"2022-06-06T01:00:00.000Z","treatmentName":"massage","userId":100},{"id":1654491600,"dateTime":"2022-06-06T05:00:00.000Z","treatmentName":"facial","userId":100},{"id":1654574400,"dateTime":"2022-06-07T04:00:00.000Z","treatmentName":"scrub"},{"id":1654581600,"dateTime":"2022-06-07T06:00:00.000Z","treatmentName":"massage"},{"id":1654653600,"dateTime":"2022-06-08T02:00:00.000Z","treatmentName":"facial","userId":100},{"id":1654671600,"dateTime":"2022-06-08T07:00:00.000Z","treatmentName":"scrub"},{"id":1654732800,"dateTime":"2022-06-09T00:00:00.000Z","treatmentName":"scrub","userId":100},{"id":1654747200,"dateTime":"2022-06-09T04:00:00.000Z","treatmentName":"scrub"},{"id":1654833600,"dateTime":"2022-06-10T04:00:00.000Z","treatmentName":"massage"},{"id":1654840800,"dateTime":"2022-06-10T06:00:00.000Z","treatmentName":"massage","userId":100},{"id":1655082000,"dateTime":"2022-06-13T01:00:00.000Z","treatmentName":"massage","userId":100},{"id":1655096400,"dateTime":"2022-06-13T05:00:00.000Z","treatmentName":"facial"},{"id":1655179200,"dateTime":"2022-06-14T04:00:00.000Z","treatmentName":"scrub"},{"id":1655186400,"dateTime":"2022-06-14T06:00:00.000Z","treatmentName":"massage"},{"id":1655258400,"dateTime":"2022-06-15T02:00:00.000Z","treatmentName":"facial","userId":100},{"id":1655276400,"dateTime":"2022-06-15T07:00:00.000Z","treatmentName":"scrub"},{"id":1655337600,"dateTime":"2022-06-16T00:00:00.000Z","treatmentName":"scrub","userId":100},{"id":1655352000,"dateTime":"2022-06-16T04:00:00.000Z","treatmentName":"scrub","userId":100},{"id":1655438400,"dateTime":"2022-06-17T04:00:00.000Z","treatmentName":"massage","userId":100},{"id":1655445600,"dateTime":"2022-06-17T06:00:00.000Z","treatmentName":"massage","userId":100},{"id":1655686800,"dateTime":"2022-06-20T01:00:00.000Z","treatmentName":"massage","userId":100},{"id":1655701200,"dateTime":"2022-06-20T05:00:00.000Z","treatmentName":"facial"},{"id":1655784000,"dateTime":"2022-06-21T04:00:00.000Z","treatmentName":"scrub"},{"id":1655791200,"dateTime":"2022-06-21T06:00:00.000Z","treatmentName":"massage","userId":100},{"id":1655863200,"dateTime":"2022-06-22T02:00:00.000Z","treatmentName":"facial"},{"id":1655881200,"dateTime":"2022-06-22T07:00:00.000Z","treatmentName":"scrub","userId":100},{"id":1655942400,"dateTime":"2022-06-23T00:00:00.000Z","treatmentName":"scrub"},{"id":1655956800,"dateTime":"2022-06-23T04:00:00.000Z","treatmentName":"scrub","userId":100},{"id":1656043200,"dateTime":"2022-06-24T04:00:00.000Z","treatmentName":"massage","userId":100},{"id":1656050400,"dateTime":"2022-06-24T06:00:00.000Z","treatmentName":"massage"},{"id":1656291600,"dateTime":"2022-06-27T01:00:00.000Z","treatmentName":"massage"},{"id":1656306000,"dateTime":"2022-06-27T05:00:00.000Z","treatmentName":"facial","userId":100},{"id":1656388800,"dateTime":"2022-06-28T04:00:00.000Z","treatmentName":"scrub"},{"id":1656396000,"dateTime":"2022-06-28T06:00:00.000Z","treatmentName":"massage"},{"id":1656468000,"dateTime":"2022-06-29T02:00:00.000Z","treatmentName":"facial","userId":100},{"id":1656486000,"dateTime":"2022-06-29T07:00:00.000Z","treatmentName":"scrub","userId":100},{"id":1656547200,"dateTime":"2022-06-30T00:00:00.000Z","treatmentName":"scrub","userId":100},{"id":1656561600,"dateTime":"2022-06-30T04:00:00.000Z","treatmentName":"scrub","userId":100}]